[{"keyword":"Feature","type":"feature","description":"","line":2,"name":"Saucedemo Login","uri":"D:\\BOOTCAMP\\TUGAS SESI 11\\wdio-cucumber\\features\\saucedemo_login.feature","tags":[{"location":{"line":1,"column":1},"name":"@Saucedemo","id":"85b3ae62-80b9-4840-95b7-7042b888f011"},{"location":{"line":1,"column":12},"name":"@login","id":"7e959ea3-c9fb-4a46-9810-1011ed960e5b"}],"elements":[{"keyword":"Scenario","type":"scenario","description":"","name":"Successfull login","tags":[{"name":"@Saucedemo","astNodeId":"85b3ae62-80b9-4840-95b7-7042b888f011"},{"name":"@login","astNodeId":"7e959ea3-c9fb-4a46-9810-1011ed960e5b"},{"name":"@tc-1","astNodeId":"c2f89e8b-6ea7-454a-a79e-a42fcf42758a"},{"name":"@standard_user","astNodeId":"d23fec05-71aa-4fab-b1b8-3d4e9acf2d71"}],"id":"saucedemo-loginsuccessfull-login","steps":[{"arguments":[],"keyword":"Before","name":"","result":{"status":"passed","duration":1000000},"line":null,"match":{"location":"can not be determined with webdriver.io"}},{"arguments":[],"keyword":"Given","name":"user is on Saucedemo login page","result":{"status":"passed","duration":353000000},"line":null,"match":{"location":"can not be determined with webdriver.io"}},{"arguments":[],"keyword":"And","name":"user input username with \"standard_user\"","result":{"status":"passed","duration":119000000},"line":null,"match":{"location":"can not be determined with webdriver.io"}},{"arguments":[],"keyword":"And","name":"user input password with \"secret_sauce\"","result":{"status":"passed","duration":81000000},"line":null,"match":{"location":"can not be determined with webdriver.io"}},{"arguments":[],"keyword":"When","name":"user click login button","result":{"status":"passed","duration":91000000},"line":null,"match":{"location":"can not be determined with webdriver.io"}},{"arguments":[],"keyword":"Then","name":"user should redirect to the homepage","result":{"status":"passed","duration":4000000},"line":null,"match":{"location":"can not be determined with webdriver.io"}},{"arguments":[],"keyword":"After","name":"","result":{"status":"passed","duration":1000000},"line":null,"match":{"location":"can not be determined with webdriver.io"}}]}],"id":"saucedemo-login","metadata":{"browser":{"name":"chrome","version":"126.0.6478.127"},"device":"Device name not known","platform":{"name":"windows","version":"Version not known"}}}]
