[{"keyword":"Feature","type":"feature","description":"","line":3,"name":"Saucedemo Add to cart","uri":"D:\\BOOTCAMP\\TUGAS SESI 11\\wdio-cucumber\\features\\addtocart.feature","tags":[{"location":{"line":1,"column":1},"name":"@Saucedemo","id":"63ebeb70-0a41-4e8f-9f91-1838cc1a0067"},{"location":{"line":1,"column":12},"name":"@Dashboard","id":"7b68947e-4511-4720-a6b6-f173a76e5214"}],"elements":[{"keyword":"Scenario","type":"scenario","description":"","name":"add to cart satu","tags":[{"name":"@Saucedemo","astNodeId":"63ebeb70-0a41-4e8f-9f91-1838cc1a0067"},{"name":"@Dashboard","astNodeId":"7b68947e-4511-4720-a6b6-f173a76e5214"},{"name":"@tc-3","astNodeId":"ba60bb12-a332-49b2-98c4-e32a3fa63707"},{"name":"@addtocart","astNodeId":"a59b019a-aad9-4f58-af19-d50564527c62"}],"id":"saucedemo-add-to-cartadd-to-cart-satu","steps":[{"arguments":[],"keyword":"Before","name":"","result":{"status":"passed","duration":2000000},"line":null,"match":{"location":"can not be determined with webdriver.io"}},{"arguments":[],"keyword":"Given","name":"user is on Saucedemo login page","result":{"status":"passed","duration":334000000},"line":null,"match":{"location":"can not be determined with webdriver.io"}},{"arguments":[],"keyword":"And","name":"user input username with \"standard_user\"","result":{"status":"passed","duration":110000000},"line":null,"match":{"location":"can not be determined with webdriver.io"}},{"arguments":[],"keyword":"And","name":"user input password with \"secret_sauce\"","result":{"status":"passed","duration":85000000},"line":null,"match":{"location":"can not be determined with webdriver.io"}},{"arguments":[],"keyword":"When","name":"user click login button","result":{"status":"passed","duration":93000000},"line":null,"match":{"location":"can not be determined with webdriver.io"}},{"arguments":[],"keyword":"Given","name":"user is on Saucedemo Dashboard page","result":{"status":"passed","duration":110000000},"line":null,"match":{"location":"can not be determined with webdriver.io"}},{"arguments":[],"keyword":"When","name":"user click add button on catalog","result":{"status":"passed","duration":51000000},"line":null,"match":{"location":"can not be determined with webdriver.io"}},{"arguments":[],"keyword":"And","name":"user click cart icon on top righ","result":{"status":"passed","duration":41000000},"line":null,"match":{"location":"can not be determined with webdriver.io"}},{"arguments":[],"keyword":"Then","name":"user should redirect to the yourcartpage","result":{"status":"passed","duration":59000000},"line":null,"match":{"location":"can not be determined with webdriver.io"}},{"arguments":[],"keyword":"After","name":"","result":{"status":"passed","duration":1000000},"line":null,"match":{"location":"can not be determined with webdriver.io"}}]}],"id":"saucedemo-add-to-cart","metadata":{"browser":{"name":"chrome","version":"126.0.6478.127"},"device":"Device name not known","platform":{"name":"windows","version":"Version not known"}}}]
