[{"keyword":"Feature","type":"feature","description":"","line":2,"name":"Saucedemo Login","uri":"D:\\BOOTCAMP\\TUGAS SESI 11\\wdio-cucumber\\features\\saucedemo_login.feature","tags":[{"location":{"line":1,"column":1},"name":"@Saucedemo","id":"afd1c0ae-011c-4d42-8515-091117d8898d"},{"location":{"line":1,"column":12},"name":"@login","id":"b9ade054-7138-4b52-9b0d-3a7a28cd5dd9"}],"elements":[{"keyword":"Scenario","type":"scenario","description":"","name":"Successfull login dua","tags":[{"name":"@Saucedemo","astNodeId":"afd1c0ae-011c-4d42-8515-091117d8898d"},{"name":"@login","astNodeId":"b9ade054-7138-4b52-9b0d-3a7a28cd5dd9"},{"name":"@tc-2","astNodeId":"56cd1090-0206-4683-880f-4ddc3b687990"},{"name":"@visual_user","astNodeId":"b6a578e9-aa3f-49cd-803e-6d515fc43d70"}],"id":"saucedemo-loginsuccessfull-login-dua","steps":[{"arguments":[],"keyword":"Before","name":"","result":{"status":"passed","duration":3000000},"line":null,"match":{"location":"can not be determined with webdriver.io"}},{"arguments":[],"keyword":"Given","name":"user is on Saucedemo login page","result":{"status":"passed","duration":384000000},"line":null,"match":{"location":"can not be determined with webdriver.io"}},{"arguments":[],"keyword":"And","name":"user input password with \"secret_sauce\"","result":{"status":"passed","duration":249000000},"line":null,"match":{"location":"can not be determined with webdriver.io"}},{"arguments":[],"keyword":"And","name":"user input username with \"visual_user\"","result":{"status":"passed","duration":263000000},"line":null,"match":{"location":"can not be determined with webdriver.io"}},{"arguments":[],"keyword":"When","name":"user click login button","result":{"status":"passed","duration":141000000},"line":null,"match":{"location":"can not be determined with webdriver.io"}},{"arguments":[],"keyword":"Then","name":"user should redirect to the homepage","result":{"status":"passed","duration":291000000},"line":null,"match":{"location":"can not be determined with webdriver.io"}},{"arguments":[],"keyword":"After","name":"","result":{"status":"passed","duration":1000000},"line":null,"match":{"location":"can not be determined with webdriver.io"}}]}],"id":"saucedemo-login","metadata":{"browser":{"name":"MicrosoftEdge","version":"125.0.2535.79"},"device":"Device name not known","platform":{"name":"windows","version":"Version not known"}}}]
